python_local/__init__.py
python_local/server.py
python_local-0.1.0.dist-info/METADATA
python_local-0.1.0.dist-info/WHEEL
python_local-0.1.0.dist-info/entry_points.txt
python_local-0.1.0.dist-info/RECORD
