Metadata-Version: 2.3
Name: python-local
Version: 0.1.0
Summary: An MCP Server to run python locally
Author-email: Alex Velikanov <alex25368@gmail.com>
Requires-Python: >=3.12
Requires-Dist: mcp>=1.1.0
